README.md
setup.py
wordpress_cd_rancher/__init__.py
wordpress_cd_rancher/rancher.py
wordpress_cd_rancher.egg-info/PKG-INFO
wordpress_cd_rancher.egg-info/SOURCES.txt
wordpress_cd_rancher.egg-info/dependency_links.txt
wordpress_cd_rancher.egg-info/requires.txt
wordpress_cd_rancher.egg-info/top_level.txt