Metadata-Version: 1.0
Name: wordpress-cd-rancher
Version: 0.1.0
Summary: Wordpress CD driver to deploy sites to Rancher environments.
Home-page: https://github.com/rossigee/wordpress-cd-rancher
Author: Ross Golder
Author-email: ross@golder.org
License: UNKNOWN
Platform: UNKNOWN
